arcane/stackdriver.py
arcane_stackdriver-1.0.0.dist-info/WHEEL
arcane_stackdriver-1.0.0.dist-info/METADATA
arcane_stackdriver-1.0.0.dist-info/RECORD
