Metadata-Version: 2.1
Name: arcane-stackdriver
Version: 1.0.0
Summary: Override stackdriver client
Author: Arcane
Author-email: product@arcane.run
Requires-Python: >=3.6,<4.0
Classifier: Programming Language :: Python :: 3
Classifier: Programming Language :: Python :: 3.10
Classifier: Programming Language :: Python :: 3.6
Classifier: Programming Language :: Python :: 3.7
Classifier: Programming Language :: Python :: 3.8
Classifier: Programming Language :: Python :: 3.9
Requires-Dist: google-cloud-error-reporting (>=1.4.0,<2.0.0)
